spacy_affixes/__init__.py
spacy_affixes/__main__.py
spacy_affixes/eagles.py
spacy_affixes/main.py
spacy_affixes/utils.py
spacy_affixes/data/.keep
spacy_affixes-0.1.4.dist-info/AUTHORS.rst
spacy_affixes-0.1.4.dist-info/LICENSE
spacy_affixes-0.1.4.dist-info/METADATA
spacy_affixes-0.1.4.dist-info/WHEEL
spacy_affixes-0.1.4.dist-info/top_level.txt
spacy_affixes-0.1.4.dist-info/RECORD
