Metadata-Version: 2.1
Name: spacy-affixes
Version: 0.1.4
Summary: SpaCy support to split affixes for Freeling-like affixes rules and dictionaries
Home-page: https://github.com/linhd-postdata/spacy-affixes
Author: LINHD POSTDATA Project
Author-email: info@linhd.uned.es
License: Apache Software License 2.0
Keywords: spacy_affixes
Platform: UNKNOWN
Classifier: Development Status :: 2 - Pre-Alpha
Classifier: Intended Audience :: Developers
Classifier: License :: OSI Approved :: Apache Software License
Classifier: Natural Language :: English
Classifier: Programming Language :: Python :: 3.5
Classifier: Programming Language :: Python :: 3.6
Classifier: Programming Language :: Python :: 3.7
Requires-Dist: spacy (>=2.0)
